contextmodel/__init__.py
contextmodel/py.typed
contextmodel-0.2.1.dist-info/METADATA
contextmodel-0.2.1.dist-info/WHEEL
contextmodel-0.2.1.dist-info/licenses/LICENSE
contextmodel-0.2.1.dist-info/RECORD
