Metadata-Version: 2.4
Name: contextmodel
Version: 0.2.1
Summary: A nice interface to context variables
License-File: LICENSE
Requires-Python: >=3.12
